llama_index/storage/kvstore/tablestore/__init__.py
llama_index/storage/kvstore/tablestore/base.py
llama_index_storage_kvstore_tablestore-0.2.1.dist-info/METADATA
llama_index_storage_kvstore_tablestore-0.2.1.dist-info/WHEEL
llama_index_storage_kvstore_tablestore-0.2.1.dist-info/licenses/LICENSE
llama_index_storage_kvstore_tablestore-0.2.1.dist-info/RECORD
